stac_fastapi/extensions/__init__.py
stac_fastapi/extensions/py.typed
stac_fastapi/extensions/version.py
stac_fastapi/extensions/core/__init__.py
stac_fastapi/extensions/core/aggregation/__init__.py
stac_fastapi/extensions/core/aggregation/aggregation.py
stac_fastapi/extensions/core/aggregation/client.py
stac_fastapi/extensions/core/aggregation/request.py
stac_fastapi/extensions/core/aggregation/types.py
stac_fastapi/extensions/core/collection_search/__init__.py
stac_fastapi/extensions/core/collection_search/client.py
stac_fastapi/extensions/core/collection_search/collection_search.py
stac_fastapi/extensions/core/collection_search/request.py
stac_fastapi/extensions/core/fields/__init__.py
stac_fastapi/extensions/core/fields/fields.py
stac_fastapi/extensions/core/fields/request.py
stac_fastapi/extensions/core/filter/__init__.py
stac_fastapi/extensions/core/filter/client.py
stac_fastapi/extensions/core/filter/filter.py
stac_fastapi/extensions/core/filter/request.py
stac_fastapi/extensions/core/free_text/__init__.py
stac_fastapi/extensions/core/free_text/free_text.py
stac_fastapi/extensions/core/free_text/request.py
stac_fastapi/extensions/core/pagination/__init__.py
stac_fastapi/extensions/core/pagination/offset_pagination.py
stac_fastapi/extensions/core/pagination/pagination.py
stac_fastapi/extensions/core/pagination/request.py
stac_fastapi/extensions/core/pagination/token_pagination.py
stac_fastapi/extensions/core/query/__init__.py
stac_fastapi/extensions/core/query/query.py
stac_fastapi/extensions/core/query/request.py
stac_fastapi/extensions/core/sort/__init__.py
stac_fastapi/extensions/core/sort/request.py
stac_fastapi/extensions/core/sort/sort.py
stac_fastapi/extensions/core/transaction/__init__.py
stac_fastapi/extensions/core/transaction/client.py
stac_fastapi/extensions/core/transaction/request.py
stac_fastapi/extensions/core/transaction/transaction.py
stac_fastapi/extensions/third_party/__init__.py
stac_fastapi/extensions/third_party/bulk_transactions.py
stac_fastapi_extensions-6.2.0.dist-info/METADATA
stac_fastapi_extensions-6.2.0.dist-info/WHEEL
stac_fastapi_extensions-6.2.0.dist-info/RECORD
